qtit/__init__.py
qtit-0.0.0a1.dist-info/METADATA
qtit-0.0.0a1.dist-info/WHEEL
qtit-0.0.0a1.dist-info/RECORD
