Metadata-Version: 2.4
Name: qtit
Version: 0.0.0a1
Summary: coming soon
Author-email: onerandomusername <me@arielle.codes>
